ecos_api_loader/__init__.py
ecos_api_loader/ecos_api.py
ecosloader/__init__.py
ecosloader/ecos_api.py
ecosloader-0.0.8.dist-info/LICENSE
ecosloader-0.0.8.dist-info/METADATA
ecosloader-0.0.8.dist-info/WHEEL
ecosloader-0.0.8.dist-info/top_level.txt
ecosloader-0.0.8.dist-info/RECORD
